{
  "slug": "cheapest-time-to-book-flights-2026",
  "title": "The Cheapest Time to Book Flights in 2026: A Data-Driven Guide",
  "excerpt": "When should you book your flights for the lowest prices? We break down the best booking windows, cheapest days to fly, and seasonal pricing patterns.",
  "date": "2026-04-01",
  "readTime": "7 min read",
  "category": "Tips & Tricks",
  "image": "https://images.unsplash.com/photo-1436491865332-7a61a109db05?w=1200&q=80",
  "tags": ["flights", "budget", "booking-tips", "savings", "airlines"],
  "content": "Airfare is often the single largest expense in any trip budget. Knowing when to book — and when to fly — can save you hundreds or even thousands of dollars per year. Here is what the data tells us about finding the cheapest flights in 2026.\n\n## The Best Time to Book Domestic Flights\n\nFor domestic flights within the US, the sweet spot is typically 1-3 months before departure. Booking too early (4+ months) or too late (under 2 weeks) usually means higher prices. Tuesday and Wednesday departures tend to be the cheapest days to fly domestically.\n\n## The Best Time to Book International Flights\n\nInternational flights follow a different pattern. The ideal booking window is 2-8 months before departure, depending on the route. Flights to Europe are cheapest when booked 3-5 months ahead, while Asia-Pacific routes often have the best deals 5-7 months out.\n\n## Cheapest Days to Fly\n\nTuesday, Wednesday, and Saturday are generally the cheapest days to fly. Friday and Sunday are typically the most expensive due to business and weekend leisure travel demand. A midweek departure and return can save 20-40% compared to weekend flights.\n\n## Seasonal Pricing Patterns\n\nJanuary through mid-March (excluding spring break weeks) offers some of the lowest fares of the year for most routes. September through early November is another sweet spot, with mild weather at many destinations and lower demand. Peak summer (June-August) and holiday periods (Thanksgiving, Christmas, New Year) command the highest prices.\n\n## Using Fare Alerts and Comparison Tools\n\nThe most effective strategy is to combine timing knowledge with technology. Set fare alerts on flight comparison platforms to track prices for your desired route. When you see a price drop below the historical average, book immediately — good deals rarely last more than 24-48 hours.\n\n## Error Fares and Flash Sales\n\nAirlines occasionally publish mistake fares or run flash sales with dramatic discounts. Following deal alert services and being flexible with your destination can help you capitalize on these opportunities. Having a valid passport ready at all times is essential for taking advantage of surprise international deals.\n\n## The Bottom Line\n\nBook domestic flights 1-3 months ahead, international flights 2-8 months ahead, fly midweek when possible, and use price alert tools to catch deals. These simple strategies can save the average traveler $500-1,500 per year on airfare.",
  "affiliateLinks": [
    {"label": "Search Cheap Flights", "url": "https://tp.media/r?marker=TRAVELPAYOUTS_TOKEN&p=4132&u=https%3A%2F%2Fwww.aviasales.com", "provider": "TravelPayouts"},
    {"label": "Compare Flight + Hotel Packages", "url": "https://www.booking.com/flights/index.html?aid=BOOKING_AID", "provider": "Booking.com"}
  ]
}
